postgres_mcp/__init__.py
postgres_mcp/artifacts.py
postgres_mcp/server.py
postgres_mcp/database_health/__init__.py
postgres_mcp/database_health/buffer_health_calc.py
postgres_mcp/database_health/connection_health_calc.py
postgres_mcp/database_health/constraint_health_calc.py
postgres_mcp/database_health/database_health.py
postgres_mcp/database_health/index_health_calc.py
postgres_mcp/database_health/replication_calc.py
postgres_mcp/database_health/sequence_health_calc.py
postgres_mcp/database_health/vacuum_health_calc.py
postgres_mcp/dta/__init__.py
postgres_mcp/dta/dta_calc.py
postgres_mcp/dta/dta_tools.py
postgres_mcp/explain/README.md
postgres_mcp/explain/__init__.py
postgres_mcp/explain/explain_plan.py
postgres_mcp/sql/__init__.py
postgres_mcp/sql/bind_params.py
postgres_mcp/sql/extension_utils.py
postgres_mcp/sql/index.py
postgres_mcp/sql/safe_sql.py
postgres_mcp/sql/sql_driver.py
postgres_mcp/top_queries/__init__.py
postgres_mcp/top_queries/top_queries_calc.py
postgres_mcp-0.2.1.dist-info/METADATA
postgres_mcp-0.2.1.dist-info/WHEEL
postgres_mcp-0.2.1.dist-info/entry_points.txt
postgres_mcp-0.2.1.dist-info/licenses/LICENSE
postgres_mcp-0.2.1.dist-info/RECORD
